cdktf_cdktf_provider_consul/__init__.py
cdktf_cdktf_provider_consul/py.typed
cdktf_cdktf_provider_consul/_jsii/__init__.py
cdktf_cdktf_provider_consul/_jsii/provider-consul@10.1.1.jsii.tgz
cdktf_cdktf_provider_consul/acl_auth_method/__init__.py
cdktf_cdktf_provider_consul/acl_binding_rule/__init__.py
cdktf_cdktf_provider_consul/acl_policy/__init__.py
cdktf_cdktf_provider_consul/acl_role/__init__.py
cdktf_cdktf_provider_consul/acl_role_policy_attachment/__init__.py
cdktf_cdktf_provider_consul/acl_token/__init__.py
cdktf_cdktf_provider_consul/acl_token_policy_attachment/__init__.py
cdktf_cdktf_provider_consul/acl_token_role_attachment/__init__.py
cdktf_cdktf_provider_consul/admin_partition/__init__.py
cdktf_cdktf_provider_consul/agent_service/__init__.py
cdktf_cdktf_provider_consul/autopilot_config/__init__.py
cdktf_cdktf_provider_consul/catalog_entry/__init__.py
cdktf_cdktf_provider_consul/certificate_authority/__init__.py
cdktf_cdktf_provider_consul/config_entry/__init__.py
cdktf_cdktf_provider_consul/config_entry_service_defaults/__init__.py
cdktf_cdktf_provider_consul/config_entry_service_intentions/__init__.py
cdktf_cdktf_provider_consul/config_entry_service_resolver/__init__.py
cdktf_cdktf_provider_consul/config_entry_service_router/__init__.py
cdktf_cdktf_provider_consul/config_entry_service_splitter/__init__.py
cdktf_cdktf_provider_consul/config_entry_v2_exported_services/__init__.py
cdktf_cdktf_provider_consul/data_consul_acl_auth_method/__init__.py
cdktf_cdktf_provider_consul/data_consul_acl_policy/__init__.py
cdktf_cdktf_provider_consul/data_consul_acl_role/__init__.py
cdktf_cdktf_provider_consul/data_consul_acl_token/__init__.py
cdktf_cdktf_provider_consul/data_consul_acl_token_secret_id/__init__.py
cdktf_cdktf_provider_consul/data_consul_agent_config/__init__.py
cdktf_cdktf_provider_consul/data_consul_agent_self/__init__.py
cdktf_cdktf_provider_consul/data_consul_autopilot_health/__init__.py
cdktf_cdktf_provider_consul-10.1.1.dist-info/LICENSE
cdktf_cdktf_provider_consul-10.1.1.dist-info/METADATA
cdktf_cdktf_provider_consul-10.1.1.dist-info/WHEEL
cdktf_cdktf_provider_consul-10.1.1.dist-info/top_level.txt
cdktf_cdktf_provider_consul-10.1.1.dist-info/RECORD
